validator/__init__.py
validator/alpha.py
validator/is_ISO31661_alpha2.py
validator/is_after.py
validator/is_alpha.py
validator/is_ascii.py
validator/is_base32.py
validator/is_base58.py
validator/is_base64.py
validator/is_before.py
validator/is_bic.py
validator/is_boolean.py
validator/is_btc_address.py
validator/is_byte_length.py
validator/is_credit_card.py
validator/is_currency.py
validator/is_data_uri.py
validator/is_decimal.py
validator/is_divisible_by.py
validator/is_ean.py
validator/is_float.py
validator/is_int.py
validator/is_ip.py
validator/is_isrc.py
validator/is_jwt.py
validator/is_md5.py
validator/is_number.py
validator/is_port.py
validator/is_uuid.py
py.validator-0.0.8.dist-info/LICENSE
py.validator-0.0.8.dist-info/METADATA
py.validator-0.0.8.dist-info/WHEEL
py.validator-0.0.8.dist-info/top_level.txt
py.validator-0.0.8.dist-info/RECORD
